pulp_maven/__init__.py
pulp_maven/app/__init__.py
pulp_maven/app/maven_deploy_api.py
pulp_maven/app/models.py
pulp_maven/app/serializers.py
pulp_maven/app/settings.py
pulp_maven/app/urls.py
pulp_maven/app/viewsets.py
pulp_maven/app/migrations/0001_initial.py
pulp_maven/app/migrations/0001_squashed_0006_alter_mavenartifact_content_ptr_and_more.py
pulp_maven/app/migrations/0002_maven_related_names.py
pulp_maven/app/migrations/0003_mavenrepository.py
pulp_maven/app/migrations/0004_swap_distribution_models.py
pulp_maven/app/migrations/0005_mavenmetadata.py
pulp_maven/app/migrations/0006_alter_mavenartifact_content_ptr_and_more.py
pulp_maven/app/migrations/0007_alter_mavenartifact_unique_together_and_more.py
pulp_maven/app/migrations/__init__.py
pulp_maven/app/tasks/__init__.py
pulp_maven/tests/__init__.py
pulp_maven/tests/assets/simple-project/pom.xml
pulp_maven/tests/assets/simple-project/src/main/java/org/sonatype/nexus/examples/App.java
pulp_maven/tests/assets/simple-project/src/test/java/org/sonatype/nexus/examples/AppTest.java
pulp_maven/tests/functional/__init__.py
pulp_maven/tests/functional/conftest.py
pulp_maven/tests/functional/utils.py
pulp_maven/tests/functional/api/__init__.py
pulp_maven/tests/functional/api/test_crud_remotes.py
pulp_maven/tests/functional/api/test_download_content.py
pulp_maven/tests/functional/api/test_mvn_deploy.py
pulp_maven/tests/unit/__init__.py
pulp_maven/tests/unit/test_models.py
pulp_maven-0.12.0.dist-info/licenses/LICENSE
pulp_maven-0.12.0.dist-info/METADATA
pulp_maven-0.12.0.dist-info/WHEEL
pulp_maven-0.12.0.dist-info/entry_points.txt
pulp_maven-0.12.0.dist-info/top_level.txt
pulp_maven-0.12.0.dist-info/RECORD
