Metadata-Version: 2.4
Name: pulp-maven
Version: 0.12.0
Summary: pulp-maven plugin for the Pulp Project
Author-email: Pulp Team <pulp-list@redhat.com>
Project-URL: Homepage, https://pulpproject.org
Project-URL: Documentation, https://pulpproject.org/pulp_maven/
Project-URL: Repository, https://github.com/pulp/pulp_maven
Project-URL: Bug Tracker, https://github.com/pulp/pulp_maven/issues
Project-URL: Changelog, https://pulpproject.org/pulp_maven/changes/
Classifier: License :: OSI Approved :: GNU General Public License v2 or later (GPLv2+)
Classifier: Operating System :: POSIX :: Linux
Classifier: Development Status :: 4 - Beta
Classifier: Framework :: Django
Classifier: Programming Language :: Python
Classifier: Programming Language :: Python :: 3
Requires-Python: >=3.11
License-File: LICENSE
Requires-Dist: pulpcore<3.115,>=3.73.0
Dynamic: license-file
